.DS_Store
openai/.DS_Store
openai/__init__.py
openai/_openai_scripts.py
openai/api_requestor.py
openai/cli.py
openai/embeddings_utils.py
openai/error.py
openai/object_classes.py
openai/openai_object.py
openai/openai_response.py
openai/py.typed
openai/upload_progress.py
openai/util.py
openai/validators.py
openai/version.py
openai/wandb_logger.py
openai/api_resources/__init__.py
openai/api_resources/audio.py
openai/api_resources/chat_completion.py
openai/api_resources/completion.py
openai/api_resources/customer.py
openai/api_resources/deployment.py
openai/api_resources/edit.py
openai/api_resources/embedding.py
openai/api_resources/engine.py
openai/api_resources/error_object.py
openai/api_resources/file.py
openai/api_resources/fine_tune.py
openai/api_resources/fine_tuning.py
openai/api_resources/image.py
openai/api_resources/model.py
openai/api_resources/moderation.py
openai/api_resources/abstract/__init__.py
openai/api_resources/abstract/api_resource.py
openai/api_resources/abstract/createable_api_resource.py
openai/api_resources/abstract/deletable_api_resource.py
openai/api_resources/abstract/engine_api_resource.py
openai/api_resources/abstract/listable_api_resource.py
openai/api_resources/abstract/nested_resource_class_methods.py
openai/api_resources/abstract/paginatable_api_resource.py
openai/api_resources/abstract/updateable_api_resource.py
openai/api_resources/experimental/__init__.py
openai/api_resources/experimental/completion_config.py
openai/datalib/__init__.py
openai/datalib/common.py
openai/datalib/numpy_helper.py
openai/datalib/pandas_helper.py
openai/tests/__init__.py
openai/tests/test_api_requestor.py
openai/tests/test_endpoints.py
openai/tests/test_exceptions.py
openai/tests/test_file_cli.py
openai/tests/test_long_examples_validator.py
openai/tests/test_url_composition.py
openai/tests/test_util.py
openai/tests/asyncio/__init__.py
openai/tests/asyncio/test_endpoints.py
openaicustomiz-0.30.4.dist-info/LICENSE
openaicustomiz-0.30.4.dist-info/METADATA
openaicustomiz-0.30.4.dist-info/WHEEL
openaicustomiz-0.30.4.dist-info/entry_points.txt
openaicustomiz-0.30.4.dist-info/top_level.txt
openaicustomiz-0.30.4.dist-info/zip-safe
openaicustomiz-0.30.4.dist-info/RECORD
